{
  "generator-jhipster": {
    "applicationType": "gateway",
    "authenticationType": "oauth2",
    "baseName": "connect2",
    "blueprints": [],
    "buildTool": "maven",
    "cacheProvider": "ehcache",
    "clientFramework": "react",
    "clientPackageManager": "npm",
    "creationTimestamp": 1703243348017,
    "databaseType": "sql",
    "devDatabaseType": "mysql",
    "devServerPort": 9060,
    "enableHibernateCache": true,
    "enableSwaggerCodegen": "true",
    "enableTranslation": true,
    "entities": [],
    "gitCompany": "",
    "jhiPrefix": "jhi",
    "jhipsterVersion": "8.1.0",
    "jwtSecretKey": "NDEwYTI4YzJlMGM1MDU3ZTRjN2RiMDkzMzEyNDhjMmQyZjJmZTFkNDVjZGM5NWFhZDBmNTc1YzFkMjk5MzJhYmRjZjYwZTdkOWJlZmFkNTUzY2YxMWUxZDNiYWMzYWFlYmM5OTYzNTM2YzNkNWViZmE5NDViZTA5NDNlNzdjNGU=",
    "languages": ["en", "ar-ly", "fr"],
    "messageBroker": "kafka",
    "nativeLanguage": "en",
    "packageFolder": "com/tmrfcb/connect2",
    "packageName": "com.tmrfcb.connect2",
    "prodDatabaseType": "mysql",
    "reactive": true,
    "searchEngine": "elasticsearch",
    "serverPort": 8080,
    "serviceDiscoveryType": "consul",
    "skipUserManagement": true,
    "testFrameworks": [],
    "useSass": true,
    "websocket": false,
    "withAdminUi": true
  },
  "git-company": "tmrfcb",
  "git-provider": "GitHub",
  "repository-name": "connect2"
}
